heapy/__init__.py
heapy/pqueue.py
heapy/util.py
heapy-0.7.dist-info/LICENSE.md
heapy-0.7.dist-info/METADATA
heapy-0.7.dist-info/WHEEL
heapy-0.7.dist-info/top_level.txt
heapy-0.7.dist-info/RECORD
