Metadata-Version: 2.1
Name: heapy
Version: 0.7
Summary: A priority queue built with an in-place modifiable binary heap
Home-page: https://github.com/waylonflinn/heapy
Author: Waylon Flinn
Author-email: waylonflinn@gmail.com
License: UNKNOWN
Keywords: heap,priority queue,decrease-key,increase-key,dijkstra,rolling median,remove
Platform: UNKNOWN
License-File: LICENSE.md
